{
  "version": "clem",
  "book": "2Tim",
  "bookId": 55,
  "englishName": "2 Timothy",
  "testament": "NT",
  "chapters": [
    {
      "chapter": 1,
      "verses": [
        {
          "number": 1,
          "text": "Paulus Apostolus Jesu Christi per voluntatem Dei, secundum promissionem vit, qu est in Christo Jesu,"
        },
        {
          "number": 2,
          "text": "Timotheo carissimo filio: gratia, misericordia, pax a Deo Patre, et Christo Jesu Domino nostro."
        },
        {
          "number": 3,
          "text": "Gratias ago Deo, cui servio a progenitoribus in conscientia pura, quod sine intermissione habeam tui memoriam in orationibus meis, nocte ac die"
        },
        {
          "number": 4,
          "text": "desiderans te videre, memor lacrimarum tuarum, ut gaudio implear,"
        },
        {
          "number": 5,
          "text": "recordationem accipiens ejus fidei, qu est in te non ficta, qu et habitavit primum in avia tua Loide, et matre tua Eunice, certus sum autem quod et in te."
        },
        {
          "number": 6,
          "text": "Propter quam causam admoneo te ut resuscites gratiam Dei, qu est in te per impositionem manuum mearum."
        },
        {
          "number": 7,
          "text": "Non enim dedit nobis Deus spiritum timoris: sed virtutis, et dilectionis, et sobrietatis."
        },
        {
          "number": 8,
          "text": "Noli itaque erubescere testimonium Domini nostri, neque me vinctum ejus: sed collabora Evangelio secundum virtutem Dei:"
        },
        {
          "number": 9,
          "text": "qui nos liberavit, et vocavit vocatione sua sancta, non secundum opera nostra, sed secundum propositum suum, et gratiam, qu data est nobis in Christo Jesu ante tempora scularia."
        },
        {
          "number": 10,
          "text": "Manifestata est autem nunc per illuminationem Salvatoris nostri Jesu Christi, qui destruxit quidem mortem, illuminavit autem vitam, et incorruptionem per Evangelium:"
        },
        {
          "number": 11,
          "text": "in quo positus sum ego prdicator, et Apostolus, et magister gentium."
        },
        {
          "number": 12,
          "text": "Ob quam causam etiam hc patior, sed non confundor. Scio enim cui credidi, et certus sum quia potens est depositum meum servare in illum diem."
        },
        {
          "number": 13,
          "text": "Formam habe sanorum verborum, qu a me audisti in fide, et in dilectione in Christo Jesu."
        },
        {
          "number": 14,
          "text": "Bonum depositum custodi per Spiritum Sanctum, qui habitat in nobis."
        },
        {
          "number": 15,
          "text": "Scis hoc, quod aversi sunt a me omnes, qui in Asia sunt, ex quibus est Phigellus, et Hermogenes."
        },
        {
          "number": 16,
          "text": "Det misericordiam Dominus Onesiphori domui: quia spe me refrigeravit, et catenam meam non erubuit:"
        },
        {
          "number": 17,
          "text": "sed cum Romam venisset, sollicite me qusivit, et invenit."
        },
        {
          "number": 18,
          "text": "Det illi Dominus invenire misericordiam a Domino in illa die. Et quanta Ephesi ministravit mihi, tu melius nosti."
        }
      ]
    },
    {
      "chapter": 2,
      "verses": [
        {
          "number": 1,
          "text": "Tu ergo fili mi, confortare in gratia, qu est in Christo Jesu:"
        },
        {
          "number": 2,
          "text": "et qu audisti a me per multos testes, hc commenda fidelibus hominibus, qui idonei erant et alios docere."
        },
        {
          "number": 3,
          "text": "Labora sicut bonus miles Christi Jesu."
        },
        {
          "number": 4,
          "text": "Nemo militans Deo implicat se negotiis scularibus: ut ei placeat, cui se probavit."
        },
        {
          "number": 5,
          "text": "Nam et qui certat in agone, non coronatur nisi legitime certaverit."
        },
        {
          "number": 6,
          "text": "Laborantem agricolam oportet primum de fructibus percipere."
        },
        {
          "number": 7,
          "text": "Intellige qu dico: dabit enim tibi Dominus in omnibus intellectum."
        },
        {
          "number": 8,
          "text": "Memor esto Dominum Jesum Christum resurrexisse a mortuis ex semine David, secundum Evangelium meum,"
        },
        {
          "number": 9,
          "text": "in quo laboro usque ad vincula, quasi male operans: sed verbum Dei non est alligatum."
        },
        {
          "number": 10,
          "text": "Ideo omnia sustineo propter electos, ut et ipsi salutem consequantur, qu est in Christo Jesu, cum gloria clesti."
        },
        {
          "number": 11,
          "text": "Fidelis sermo: nam si commortui sumus, et convivemus:"
        },
        {
          "number": 12,
          "text": "si sustinebimus, et conregnabimus: si negaverimus, et ille negabit nos:"
        },
        {
          "number": 13,
          "text": "si non credimus, ille fidelis permanet, negare seipsum non potest."
        },
        {
          "number": 14,
          "text": "Hc commone, testificans coram Domino. Noli contendere verbis: ad nihil enim utile est, nisi ad subversionem audientium."
        },
        {
          "number": 15,
          "text": "Sollicite cura teipsum probabilem exhibere Deo, operarium inconfusibilem, recte tractantem verbum veritatis."
        },
        {
          "number": 16,
          "text": "Profana autem et vaniloquia devita: multum enim proficiunt ad impietatem:"
        },
        {
          "number": 17,
          "text": "et sermo eorum ut cancer serpit: ex quibus est Hymenus et Philetus,"
        },
        {
          "number": 18,
          "text": "qui a veritate exciderunt, dicentes resurrectionem esse jam factam, et subverterunt quorumdam fidem."
        },
        {
          "number": 19,
          "text": "Sed firmum fundamentum Dei stat, habens signaculum hoc: cognovit Dominus qui sunt ejus, et discedat ab iniquitate omnis qui nominat nomen Domini."
        },
        {
          "number": 20,
          "text": "In magna autem domo non solum sunt vasa aurea, et argentea, sed et lignea, et fictilia: et qudam quidem in honorem, qudam autem in contumeliam."
        },
        {
          "number": 21,
          "text": "Si quis ergo emundaverit se ab istis, erit vas in honorem sanctificatum, et utile Domino ad omne opus bonum paratum."
        },
        {
          "number": 22,
          "text": "Juvenilia autem desideria fuge, sectare vero justitiam, fidem, spem, caritatem, et pacem cum iis qui invocant Dominum de corde puro."
        },
        {
          "number": 23,
          "text": "Stultas autem et sine disciplina qustiones devita: sciens quia generant lites."
        },
        {
          "number": 24,
          "text": "Servum autem Domini non oportet litigare: sed mansuetum esse ad omnes, docibilem, patientem,"
        },
        {
          "number": 25,
          "text": "cum modestia corripientem eos qui resistunt veritati, nequando Deus det illis pnitentiam ad cognoscendam veritatem,"
        },
        {
          "number": 26,
          "text": "et resipiscant a diaboli laqueis, a quo captivi tenentur ad ipsius voluntatem."
        }
      ]
    },
    {
      "chapter": 3,
      "verses": [
        {
          "number": 1,
          "text": "Hoc autem scito, quod in novissimis diebus instabunt tempora periculosa:"
        },
        {
          "number": 2,
          "text": "erunt homines seipsos amantes, cupidi, elati, superbi, blasphemi, parentibus non obedientes, ingrati, scelesti,"
        },
        {
          "number": 3,
          "text": "sine affectione, sine pace, criminatores, incontinentes, immites, sine benignitate,"
        },
        {
          "number": 4,
          "text": "proditores, protervi, tumidi, et voluptatum amatores magis quam Dei:"
        },
        {
          "number": 5,
          "text": "habentes speciem quidem pietatis, virtutem autem ejus abnegantes. Et hos devita:"
        },
        {
          "number": 6,
          "text": "ex his enim sunt qui penetrant domos, et captivas ducunt mulierculas oneratas peccatis, qu ducuntur variis desideriis:"
        },
        {
          "number": 7,
          "text": "semper discentes, et numquam ad scientiam veritatis pervenientes."
        },
        {
          "number": 8,
          "text": "Quemadmodum autem Jannes et Mambres restiterunt Moysi: ita et hi resistunt veritati, homines corrupti mente, reprobi circa fidem;"
        },
        {
          "number": 9,
          "text": "sed ultra non proficient: insipientia enim eorum manifesta erit omnibus, sicut et illorum fuit."
        },
        {
          "number": 10,
          "text": "Tu autem assecutus es meam doctrinam, institutionem, propositum, fidem, longanimitatem, dilectionem, patientiam,"
        },
        {
          "number": 11,
          "text": "persecutiones, passiones: qualia mihi facta sunt Antiochi, Iconii, et Lystris: quales persecutiones sustinui, et ex omnibus eripuit me Dominus."
        },
        {
          "number": 12,
          "text": "Et omnes, qui pie volunt vivere in Christo Jesu, persecutionem patientur."
        },
        {
          "number": 13,
          "text": "Mali autem homines et seductores proficient in pejus, errantes, et in errorem mittentes."
        },
        {
          "number": 14,
          "text": "Tu vero permane in iis qu didicisti, et credita sunt tibi: sciens a quo didiceris:"
        },
        {
          "number": 15,
          "text": "et quia ab infantia sacras litteras nosti, qu te possunt instruere ad salutem, per fidem qu est in Christo Jesu."
        },
        {
          "number": 16,
          "text": "Omnis Scriptura divinitus inspirata utilis est ad docendum, ad arguendum, ad corripiendum, et erudiendum in justitia:"
        },
        {
          "number": 17,
          "text": "ut perfectus sit homo Dei, ad omne opus bonum instructus."
        }
      ]
    },
    {
      "chapter": 4,
      "verses": [
        {
          "number": 1,
          "text": "Testificor coram Deo, et Jesu Christo, qui judicaturus est vivos et mortuos, per adventum ipsius, et regnum ejus:"
        },
        {
          "number": 2,
          "text": "prdica verbum, insta opportune, importune: argue, obsecra, increpa in omni patientia, et doctrina."
        },
        {
          "number": 3,
          "text": "Erit enim tempus, cum sanam doctrinam non sustinebunt, sed ad sua desideria coacervabunt sibi magistros, prurientes auribus,"
        },
        {
          "number": 4,
          "text": "et a veritate quidem auditum avertent, ad fabulas autem convertentur."
        },
        {
          "number": 5,
          "text": "Tu vero vigila, in omnibus labora, opus fac evangelist, ministerium tuum imple. Sobrius esto."
        },
        {
          "number": 6,
          "text": "Ego enim jam delibor, et tempus resolutionis me instat."
        },
        {
          "number": 7,
          "text": "Bonum certamen certavi, cursum consummavi, fidem servavi."
        },
        {
          "number": 8,
          "text": "In reliquo reposita est mihi corona justiti, quam reddet mihi Dominus in illa die, justus judex: non solum autem mihi, sed et iis, qui diligunt adventum ejus. Festina ad me venire cito."
        },
        {
          "number": 9,
          "text": "Demas enim me reliquit, diligens hoc sculum, et abiit Thessalonicam:"
        },
        {
          "number": 10,
          "text": "Crescens in Galatiam, Titus in Dalmatiam."
        },
        {
          "number": 11,
          "text": "Lucas est mecum solus. Marcum assume, et adduc tecum: est enim mihi utilis in ministerium."
        },
        {
          "number": 12,
          "text": "Tychicum autem misi Ephesum."
        },
        {
          "number": 13,
          "text": "Penulam, quam reliqui Troade apud Carpum, veniens affer tecum, et libros, maxime autem membranas."
        },
        {
          "number": 14,
          "text": "Alexander rarius multa mala mihi ostendit: reddet illi Dominus secundum opera ejus:"
        },
        {
          "number": 15,
          "text": "quem et tu devita: valde enim restitit verbis nostris."
        },
        {
          "number": 16,
          "text": "In prima mea defensione nemo mihi affuit, sed omnes me dereliquerunt: non illis imputetur."
        },
        {
          "number": 17,
          "text": "Dominus autem mihi astitit, et confortavit me, ut per me prdicatio impleatur, et audiant omnes gentes: et liberatus sum de ore leonis."
        },
        {
          "number": 18,
          "text": "Liberavit me Dominus ab omni opere malo: et salvum faciet in regnum suum cleste, cui gloria in scula sculorum. Amen."
        },
        {
          "number": 19,
          "text": "Saluta Priscam, et Aquilam, et Onesiphori domum."
        },
        {
          "number": 20,
          "text": "Erastus remansit Corinthi. Trophimum autem reliqui infirmum Mileti."
        },
        {
          "number": 21,
          "text": "Festina ante hiemem venire. Salutant te Eubulus, et Pudens, et Linus, et Claudia, et fratres omnes."
        },
        {
          "number": 22,
          "text": "Dominus Jesus Christus cum spiritu tuo. Gratia vobiscum. Amen."
        }
      ]
    }
  ]
}
